google_workspace_mcp_stateless.py
main.py
main_new.py
auth/__init__.py
auth/google_auth.py
auth/oauth_callback_server.py
auth/oauth_responses.py
auth/scopes.py
auth/service_decorator.py
auth/token_auth.py
core/__init__.py
core/comments.py
core/context.py
core/server.py
core/session_server.py
core/session_transport.py
core/utils.py
gcalendar/__init__.py
gcalendar/calendar_tools.py
gcalendar/calendar_tools_new.py
gchat/__init__.py
gchat/chat_tools.py
gchat/chat_tools_new.py
gdocs/__init__.py
gdocs/docs_tools.py
gdocs/docs_tools_new.py
gdrive/__init__.py
gdrive/drive_tools.py
gdrive/drive_tools_new.py
gforms/__init__.py
gforms/forms_tools.py
gforms/forms_tools_new.py
gmail/__init__.py
gmail/gmail_tools.py
gmail/gmail_tools_new.py
gsheets/__init__.py
gsheets/sheets_tools.py
gsheets/sheets_tools_new.py
gslides/__init__.py
gslides/slides_tools.py
gslides/slides_tools_new.py
gtasks/__init__.py
gtasks/tasks_tools.py
gtasks/tasks_tools_new.py
workspace_mcp_http-0.0.8.dist-info/licenses/LICENSE
workspace_mcp_http-0.0.8.dist-info/METADATA
workspace_mcp_http-0.0.8.dist-info/WHEEL
workspace_mcp_http-0.0.8.dist-info/entry_points.txt
workspace_mcp_http-0.0.8.dist-info/top_level.txt
workspace_mcp_http-0.0.8.dist-info/RECORD
